texventure/__init__.py
texventure/engine.py
texventure/event_generators.py
texventure/generator.py
texventure/main.py
texventure/models.py
texventure/save_manager.py
texventure/ui.py
texventure-0.1.0.dist-info/METADATA
texventure-0.1.0.dist-info/WHEEL
texventure-0.1.0.dist-info/entry_points.txt
texventure-0.1.0.dist-info/RECORD
