Metadata-Version: 2.4
Name: texventure
Version: 0.1.0
Summary: A text-based adventure game generator and engine
Project-URL: Homepage, https://github.com/yourusername/texventure
Project-URL: Repository, https://github.com/yourusername/texventure
Project-URL: Issues, https://github.com/yourusername/texventure/issues
Author-email: Your Name <your.email@example.com>
Keywords: adventure,game,interactive-fiction,text-adventure
Classifier: Development Status :: 3 - Alpha
Classifier: Intended Audience :: End Users/Desktop
Classifier: License :: OSI Approved :: MIT License
Classifier: Programming Language :: Python :: 3
Classifier: Programming Language :: Python :: 3.12
Classifier: Topic :: Games/Entertainment
Requires-Python: >=3.12
Requires-Dist: pydantic>=2.11.7
Requires-Dist: pytest>=8.4.1
Requires-Dist: requests>=2.32.4
Requires-Dist: rich>=14.0.0
Requires-Dist: toml>=0.10.2
